mohand_plugin_otp/__init__.py
mohand_plugin_otp/hand.py
mohand_plugin_otp/main.py
mohand_plugin_otp/version.py
mohand_plugin_otp-1.0.0.post0.dist-info/METADATA
mohand_plugin_otp-1.0.0.post0.dist-info/RECORD
mohand_plugin_otp-1.0.0.post0.dist-info/WHEEL
mohand_plugin_otp-1.0.0.post0.dist-info/entry_points.txt
mohand_plugin_otp-1.0.0.post0.dist-info/top_level.txt
