Metadata-Version: 2.1
Name: mohand-plugin-otp
Version: 1.0.0.post0
Summary: MoHand插件，用以提供定制化的一次性密码生成服务
Home-page: https://github.com/littlemo/mohand-plugin-otp
Author: moear developers
Author-email: moore@moorehy.com
Maintainer: littlemo
Maintainer-email: moore@moorehy.com
License: GPLv3
Project-URL: Documentation, http://mohand-plugin-otp.rtfd.io/
Project-URL: Tracker, https://github.com/littlemo/mohand-plugin-otp/issues
Project-URL: Source, https://github.com/littlemo/mohand-plugin-otp
Keywords: mohand plugin otp
Platform: UNKNOWN
Classifier: Development Status :: 4 - Beta
Classifier: Environment :: Console
Classifier: Environment :: MacOS X
Classifier: Intended Audience :: Developers
Classifier: License :: OSI Approved :: GNU General Public License v3 (GPLv3)
Classifier: Natural Language :: Chinese (Simplified)
Classifier: Operating System :: MacOS
Classifier: Operating System :: POSIX :: Linux
Classifier: Programming Language :: Python
Classifier: Programming Language :: Python :: 2
Classifier: Programming Language :: Python :: 2.7
Classifier: Programming Language :: Python :: 3
Classifier: Programming Language :: Python :: 3.5
Classifier: Topic :: Communications :: Email
Classifier: Topic :: Documentation :: Sphinx
Classifier: Topic :: Software Development :: Testing :: Unit
Classifier: Topic :: Software Development :: Libraries :: Python Modules
Classifier: Topic :: Software Development :: Version Control :: Git
Classifier: Topic :: Terminals
Classifier: Topic :: Text Editors :: Emacs
Classifier: Topic :: Utilities
Requires-Python: >=2.7
Requires-Dist: mohand (>=1.0.0)
Requires-Dist: pyotp (>=2.2.6)
